[
  {
    "date": "2026-07-24T14:46:35.994Z",
    "status": "Delays",
    "details": [
      "Northbound: 96 St-bound trains are having longer wait times between Beverley Rd and Parkside Av (up to 13 mins, normally every 11 mins).",
      "Southbound: Coney Island - Stillwell Av-bound trains are having longer wait times between 96 St and Canal St (up to 12 mins, normally every 10 mins)."
    ]
  },
  {
    "date": "2026-07-23T15:03:59.179Z",
    "status": "Good Service",
    "details": []
  },
  {
    "date": "2026-07-22T14:57:28.720Z",
    "status": "Service Change",
    "details": [
      "Northbound: Some 96 St-bound trains are making local stops between Times Sq - 42 St and 57 St - 7 Av."
    ]
  },
  {
    "date": "2026-07-21T14:56:42.665Z",
    "status": "Delays",
    "details": [
      "Southbound: Coney Island - Stillwell Av-bound trains are having longer wait times between Ocean Pkwy and Coney Island - Stillwell Av (up to 12 mins, normally every 10 mins)."
    ]
  },
  {
    "date": "2026-07-19T14:21:49.204Z",
    "status": "Delays",
    "details": [
      "Northbound: 96 St-bound trains are having longer wait times between Canal St and DeKalb Av (up to 13 mins, normally every 11 mins)."
    ]
  },
  {
    "date": "2026-07-18T14:17:15.654Z",
    "status": "Good Service",
    "details": []
  },
  {
    "date": "2026-07-17T14:26:31.557Z",
    "status": "Delays",
    "details": [
      "Northbound: 96 St-bound trains are having longer wait times between Canal St and 57 St - 7 Av (up to 28 mins, normally every 12 mins).",
      "Southbound: Coney Island - Stillwell Av-bound trains are having longer wait times between Times Sq - 42 St and Kings Hwy (up to 14 mins, normally every 10 mins)."
    ]
  },
  {
    "date": "2026-07-16T14:54:00.021Z",
    "status": "Service Change",
    "details": [
      "<Q> trains are running between 96 St and Brighton Beach."
    ]
  },
  {
    "date": "2026-07-15T14:43:18.452Z",
    "status": "Delays",
    "details": [
      "Northbound: 96 St-bound trains are having longer wait times between 72 St and 96 St (up to 14 mins, normally every 11 mins).",
      "Southbound: Coney Island - Stillwell Av-bound trains are having longer wait times at Sheepshead Bay (up to 14 mins, normally every 10 mins)."
    ]
  },
  {
    "date": "2026-07-14T14:43:32.883Z",
    "status": "Delays",
    "details": [
      "Southbound: Coney Island - Stillwell Av-bound trains are taking 6 mins longer to travel between Canal St and Church Av."
    ]
  },
  {
    "date": "2026-07-12T14:24:43.094Z",
    "status": "Good Service",
    "details": []
  },
  {
    "date": "2026-07-11T14:20:07.703Z",
    "status": "Good Service",
    "details": []
  },
  {
    "date": "2026-07-10T15:27:49.140Z",
    "status": "Delays",
    "details": [
      "Northbound: 96 St-bound trains are having longer wait times between Beverley Rd and Parkside Av (up to 15 mins, normally every 11 mins).",
      "Southbound: Coney Island - Stillwell Av-bound trains are having longer wait times between Avenue H and Avenue J (up to 12 mins, normally every 10 mins)."
    ]
  },
  {
    "date": "2026-07-09T15:54:27.556Z",
    "status": "Good Service",
    "details": []
  },
  {
    "date": "2026-07-08T15:10:49.558Z",
    "status": "Delays",
    "details": [
      "Northbound: 96 St-bound trains are having longer wait times between 7 Av and DeKalb Av (up to 18 mins, normally every 11 mins).",
      "Southbound: Coney Island - Stillwell Av-bound trains are having longer wait times at Brighton Beach (up to 13 mins, normally every 10 mins)."
    ]
  },
  {
    "date": "2026-07-07T15:41:27.996Z",
    "status": "Delays",
    "details": [
      "Northbound: 96 St-bound trains are having longer wait times at Canal St (up to 17 mins, normally every 11 mins).",
      "Southbound: Coney Island - Stillwell Av-bound trains are taking 5 mins longer to travel between Canal St and Parkside Av."
    ]
  },
  {
    "date": "2026-07-06T16:13:56.566Z",
    "status": "Delays",
    "details": [
      "Northbound: 96 St-bound trains are having longer wait times between Coney Island - Stillwell Av and 72 St (up to 16 mins, normally every 9 mins).",
      "Southbound: Coney Island - Stillwell Av-bound trains are having longer wait times between Parkside Av and Avenue H (up to 18 mins, normally every 10 mins)."
    ]
  },
  {
    "date": "2026-07-05T14:26:53.337Z",
    "status": "Delays",
    "details": [
      "Southbound: Coney Island - Stillwell Av-bound trains are having longer wait times between Atlantic Av - Barclays Ctr and Kings Hwy (up to 16 mins, normally every 13 mins)."
    ]
  },
  {
    "date": "2026-07-04T14:24:51.912Z",
    "status": "Delays",
    "details": [
      "Southbound: Coney Island - Stillwell Av-bound trains are having longer wait times between Prospect Park and Parkside Av (up to 15 mins, normally every 12 mins)."
    ]
  },
  {
    "date": "2026-07-03T15:03:07.577Z",
    "status": "Delays",
    "details": [
      "Northbound: 96 St-bound trains are having longer wait times between Parkside Av and Prospect Park (up to 12 mins, normally every 9 mins).",
      "Southbound: Coney Island - Stillwell Av-bound trains are having longer wait times at 7 Av (up to 14 mins, normally every 11 mins)."
    ]
  },
  {
    "date": "2026-07-02T13:33:48.136Z",
    "status": "Service Change",
    "details": [
      "Northbound: Some 96 St-bound trains are skipping Neck Rd, and Avenue U."
    ]
  },
  {
    "date": "2026-07-01T13:47:58.034Z",
    "status": "Service Change",
    "details": [
      "Northbound: Some 96 St-bound trains are skipping Neck Rd, and Avenue U."
    ]
  },
  {
    "date": "2026-06-30T13:35:03.719Z",
    "status": "Service Change",
    "details": [
      "Northbound: Some 96 St-bound trains are skipping Neck Rd, and Avenue U."
    ]
  },
  {
    "date": "2026-06-29T14:23:05.960Z",
    "status": "Delays",
    "details": [
      "Southbound: Coney Island - Stillwell Av-bound trains are having longer wait times between 7 Av and Brighton Beach (up to 15 mins, normally every 10 mins)."
    ]
  },
  {
    "date": "2026-06-28T13:32:19.670Z",
    "status": "Good Service",
    "details": []
  },
  {
    "date": "2026-06-27T13:32:28.342Z",
    "status": "Delays",
    "details": [
      "Southbound: Coney Island - Stillwell Av-bound trains are having longer wait times between Church Av and Ocean Pkwy (up to 18 mins, normally every 12 mins)."
    ]
  },
  {
    "date": "2026-06-26T13:40:26.509Z",
    "status": "Delays",
    "details": [
      "Southbound: Coney Island - Stillwell Av-bound trains are having longer wait times between 7 Av and Ocean Pkwy (up to 12 mins, normally every 10 mins)."
    ]
  },
  {
    "date": "2026-06-25T13:42:43.661Z",
    "status": "Good Service",
    "details": []
  },
  {
    "date": "2026-06-24T13:43:03.822Z",
    "status": "Delays",
    "details": [
      "Southbound: Coney Island - Stillwell Av-bound trains are having longer wait times between 34 St - Herald Sq and 14 St - Union Sq (up to 14 mins, normally every 10 mins)."
    ]
  },
  {
    "date": "2026-06-23T13:51:25.377Z",
    "status": "Service Change",
    "details": [
      "Southbound: Coney Island - Stillwell Av-bound trains are running in 2 sections: between 96 St and Coney Island - Stillwell Av, and between 36 St and Coney Island - Stillwell Av via <N>."
    ]
  }
]